apkscan/__init__.py
apkscan/_version.py
apkscan/apkscan.py
apkscan/concurrent_executor.py
apkscan/decompiler.py
apkscan/included_secret_locators.py
apkscan/main.py
apkscan/secret_scanner.py
apkscan/secret_locators/all_secret_locators.json
apkscan/secret_locators/aws.json
apkscan/secret_locators/azure.json
apkscan/secret_locators/cloud.json
apkscan/secret_locators/curated.json
apkscan/secret_locators/default.json
apkscan/secret_locators/endpoints.json
apkscan/secret_locators/gcp.json
apkscan/secret_locators/generic.json
apkscan/secret_locators/gitleaks.toml
apkscan/secret_locators/high-confidence.yml
apkscan/secret_locators/key_locators.json
apkscan/secret_locators/leakin-regexes.yml
apkscan/secret_locators/locator_sort.py
apkscan/secret_locators/nuclei-regexes.yml
apkscan/secret_locators/secret.json
apkscan-0.4.0.dist-info/LICENSE
apkscan-0.4.0.dist-info/METADATA
apkscan-0.4.0.dist-info/WHEEL
apkscan-0.4.0.dist-info/entry_points.txt
apkscan-0.4.0.dist-info/top_level.txt
apkscan-0.4.0.dist-info/RECORD
