Metadata-Version: 2.1
Name: apkscan
Version: 0.4.0
Summary: Scan for secrets, endpoints, and other sensitive data after decompiling and deobfuscating Android files. (.apk, .xapk, .dex, .jar, .class, .smali, .zip, .aar, .arsc, .aab, .jadx.kts)
Home-page: https://github.com/LucasFaudman/apkscan.git
Author: Lucas Faudman
Author-email: Lucas Faudman <lucasfaudman@gmail.com>
License: MIT License
Project-URL: Homepage, https://github.com/LucasFaudman/apkscan.git
Project-URL: Repository, https://github.com/LucasFaudman/apkscan.git
Keywords: secret scanner,jadx,decompile,android,java,security,mobile,decompiler,concurrency,penetration-testing,apktool,security-tools,fernflower,cfr,procyon,enjarify,krakatau,secret-scanning,decompiler-java,secret-scanner,apk,xapk,dex,jar,class,smali,zip,aar,arsc,aab,jadx.kts
Classifier: Development Status :: 4 - Beta
Classifier: Intended Audience :: Developers
Classifier: License :: OSI Approved :: MIT License
Classifier: Programming Language :: Python :: 3
Classifier: Programming Language :: Python :: 3.10
Classifier: Programming Language :: Python :: 3.11
Classifier: Programming Language :: Python :: 3.12
Classifier: Operating System :: OS Independent
Classifier: Topic :: Software Development :: Libraries
Classifier: Topic :: Software Development :: Libraries :: Python Modules
Classifier: Topic :: Security
Classifier: Topic :: Utilities
Requires-Python: >=3.10
License-File: LICENSE
Requires-Dist: enjarify-adapter
Requires-Dist: pyyaml
Provides-Extra: mypyc
Requires-Dist: mypy[mypyc]; extra == "mypyc"
Requires-Dist: mypy_extensions; extra == "mypyc"
